mcp_wolfram_alpha/__init__.py
mcp_wolfram_alpha/server.py
mcp_wolfram_alpha/wolfram_client.py
mcp_wolfram_alpha-0.2.1.dist-info/METADATA
mcp_wolfram_alpha-0.2.1.dist-info/WHEEL
mcp_wolfram_alpha-0.2.1.dist-info/entry_points.txt
mcp_wolfram_alpha-0.2.1.dist-info/licenses/LICENSE
mcp_wolfram_alpha-0.2.1.dist-info/RECORD
