Metadata-Version: 2.4
Name: mcp-wolfram-alpha
Version: 0.2.1
Summary: A MCP server to connect to wolfram alpha API.
Author-email: TerminalMan <84923604+SecretiveShell@users.noreply.github.com>
License-File: LICENSE
Requires-Python: >=3.12
Requires-Dist: httpx>=0.28.1
Requires-Dist: mcp>=1.2.0
Requires-Dist: wolframalpha>=5.1.3
